calculator.py
helloworld.py
Python_DevOps-0.19.dist-info/LICENSE
Python_DevOps-0.19.dist-info/METADATA
Python_DevOps-0.19.dist-info/WHEEL
Python_DevOps-0.19.dist-info/top_level.txt
Python_DevOps-0.19.dist-info/RECORD
